crackie/__init__.py
crackie-1.0.2.dist-info/METADATA
crackie-1.0.2.dist-info/WHEEL
crackie-1.0.2.dist-info/licenses/LICENSE.txt
crackie-1.0.2.dist-info/RECORD
