Metadata-Version: 2.4
Name: crackie
Version: 1.0.2
Summary: A simple, silly library to generate combinations
Project-URL: Homepage, https://gitlab.com/pablobm/crackie
Author-email: Pablo Brasero Moreno <pablo@pablobm.com>
License-Expression: MIT
License-File: LICENSE.txt
Classifier: Development Status :: 5 - Production/Stable
Classifier: Intended Audience :: Education
Classifier: Intended Audience :: System Administrators
Classifier: Programming Language :: Python
Classifier: Topic :: Security
Requires-Python: >=3.5
